thundra_debugger-0.0.7.dist-info/METADATA
thundra_debugger-0.0.7.dist-info/top_level.txt
thundra_debugger-0.0.7.dist-info/RECORD
thundra_debugger-0.0.7.dist-info/WHEEL
tracepointdebug/__init__.py
tracepointdebug/cdbg_native.cpython-38-x86_64-linux-gnu.so
tracepointdebug/broker/broker_manager.py
tracepointdebug/broker/__init__.py
tracepointdebug/broker/ws_app.py
tracepointdebug/broker/broker_credentials.py
tracepointdebug/broker/broker_message_callback.py
tracepointdebug/broker/broker_client.py
tracepointdebug/broker/response/__init__.py
tracepointdebug/broker/response/response.py
tracepointdebug/broker/response/base_response.py
tracepointdebug/broker/event/application_status_event.py
tracepointdebug/broker/event/__init__.py
tracepointdebug/broker/event/base_event.py
tracepointdebug/broker/event/event.py
tracepointdebug/broker/handler/__init__.py
tracepointdebug/broker/handler/response/__init__.py
tracepointdebug/broker/handler/response/response_handler.py
tracepointdebug/broker/handler/request/__init__.py
tracepointdebug/broker/handler/request/request_handler.py
tracepointdebug/broker/application/application_status_provider.py
tracepointdebug/broker/application/__init__.py
tracepointdebug/broker/application/application_status.py
tracepointdebug/broker/request/__init__.py
tracepointdebug/broker/request/filter_tracepoints_request.py
tracepointdebug/broker/request/request.py
tracepointdebug/broker/request/base_request.py
tracepointdebug/external/__init__.py
tracepointdebug/external/googleclouddebugger/conditional_breakpoint.cc
tracepointdebug/external/googleclouddebugger/imphook2.py
tracepointdebug/external/googleclouddebugger/bytecode_manipulator.cc
tracepointdebug/external/googleclouddebugger/__init__.py
tracepointdebug/external/googleclouddebugger/module_utils2.py
tracepointdebug/external/googleclouddebugger/rate_limit.cc
tracepointdebug/external/googleclouddebugger/breakpoints_manager.py
tracepointdebug/external/googleclouddebugger/capture_collector.py
tracepointdebug/external/googleclouddebugger/bytecode_breakpoint.cc
tracepointdebug/external/googleclouddebugger/python_util.cc
