Metadata-Version: 2.1
Name: thundra-debugger
Version: 0.0.7
Summary: Thundra Python Debugger
Home-page: https://thundra.io/
Author: Thundra
Author-email: python@thundra.io
License: UNKNOWN
Platform: UNKNOWN
Classifier: Development Status :: 5 - Production/Stable
Classifier: Intended Audience :: Developers
Classifier: Intended Audience :: System Administrators
Classifier: Programming Language :: Python :: 2
Classifier: Programming Language :: Python :: 2.7
Classifier: Programming Language :: Python :: 3
Classifier: Programming Language :: Python :: 3.5
Classifier: Programming Language :: Python :: 3.6
Classifier: Programming Language :: Python :: 3.7
Classifier: Programming Language :: Python :: 3.8
Requires-Python: >=2.7, !=3.0.*, !=3.1.*, !=3.2.*, !=3.3.*, !=3.4.*, !=3.5.*
Requires-Dist: six (>=1.11)
Requires-Dist: websocket-client (>=0.56.0)
Requires-Dist: futures
Requires-Dist: thundra
Requires-Dist: simplejson
Requires-Dist: antlr4-python3-runtime (==4.9.2)
